timemesh/__init__.py
timemesh/data_loader.py
timemesh/data_split.py
timemesh/preprocessing.py
timemesh-0.2.2.dist-info/METADATA
timemesh-0.2.2.dist-info/WHEEL
timemesh-0.2.2.dist-info/entry_points.txt
timemesh-0.2.2.dist-info/RECORD
